{"results": [{"465, 93": [{"std_dev": 0.0, "x": "465", "ave_count": 5, "MAC": "58:f3:9c:a0:b3:52", "LEVEL": -83.0, "y": "93"}], "418, 255": [{"std_dev": 0.0, "x": "418", "ave_count": 5, "MAC": "58:f3:9c:d0:19:92", "LEVEL": -69.0, "y": "255"}], "261, 223": [{"std_dev": 0.0, "x": "261", "ave_count": 1, "MAC": "58:f3:9c:de:d9:02", "LEVEL": -90.0, "y": "223"}], "522, 479": [{"std_dev": 75.99999999999997, "x": "522", "ave_count": 5, "MAC": "10:05:ca:73:83:56", "LEVEL": -62.0, "y": "479"}], "382, 313": [{"std_dev": 29.199999999999964, "x": "382", "ave_count": 5, "MAC": "10:05:ca:80:fb:86", "LEVEL": -69.6, "y": "313"}], "416, 142": [{"std_dev": 80.79999999999998, "x": "416", "ave_count": 5, "MAC": "58:f3:9c:e8:55:36", "LEVEL": -54.8, "y": "142"}], "410, 382": [{"std_dev": 0.0, "x": "410", "ave_count": 1, "MAC": "58:f3:9c:e1:43:1d", "LEVEL": -76.0, "y": "382"}], "243, 223": [{"std_dev": 80.0, "x": "243", "ave_count": 5, "MAC": "58:f3:9c:de:d9:02", "LEVEL": -87.0, "y": "223"}], "488, 92": [{"std_dev": 24.749999999999982, "x": "488", "ave_count": 4, "MAC": "58:f3:9c:e8:d2:16", "LEVEL": -73.25, "y": "92"}], "829, 168": [{"std_dev": 0.0, "x": "829", "ave_count": 1, "MAC": "74:26:ac:b4:94:b2", "LEVEL": -86.0, "y": "168"}], "97, 560": [{"std_dev": 0.0, "x": "97", "ave_count": 1, "MAC": "58:f3:9c:e3:00:36", "LEVEL": -73.0, "y": "560"}], "218, 312": [{"std_dev": 4.666666666666664, "x": "218", "ave_count": 3, "MAC": "58:f3:9c:e8:38:96", "LEVEL": -69.33333333333333, "y": "312"}], "108, 313": [{"std_dev": 147.20000000000005, "x": "108", "ave_count": 5, "MAC": "58:f3:9c:e8:33:f6", "LEVEL": -77.4, "y": "313"}], "80, 464": [{"std_dev": 0.0, "x": "80", "ave_count": 1, "MAC": "58:f3:9c:d7:8e:e6", "LEVEL": -86.0, "y": "464"}], "409, 347": [{"std_dev": 0.0, "x": "409", "ave_count": 5, "MAC": "58:f3:9c:d7:95:fc", "LEVEL": -84.0, "y": "347"}], "334, 421": [{"std_dev": 0.0, "x": "334", "ave_count": 1, "MAC": "58:f3:9c:e4:79:ad", "LEVEL": -86.0, "y": "421"}], "335, 469": [{"std_dev": 83.19999999999996, "x": "335", "ave_count": 5, "MAC": "58:f3:9c:e1:47:e6", "LEVEL": -78.6, "y": "469"}], "125, 313": [{"std_dev": 66.66666666666664, "x": "125", "ave_count": 3, "MAC": "58:f3:9c:bb:86:1d", "LEVEL": -75.66666666666667, "y": "313"}], "552, 104": [{"std_dev": 0.0, "x": "552", "ave_count": 5, "MAC": "58:f3:9c:ac:fa:82", "LEVEL": -88.0, "y": "104"}], "738, 230": [{"std_dev": 0.0, "x": "738", "ave_count": 5, "MAC": "58:f3:9c:e8:d2:dd", "LEVEL": -84.0, "y": "230"}], "338, 450": [{"std_dev": 58.79999999999997, "x": "338", "ave_count": 5, "MAC": "58:f3:9c:e1:47:e6", "LEVEL": -73.2, "y": "450"}], "709, 238": [{"std_dev": 0.0, "x": "709", "ave_count": 1, "MAC": "58:f3:9c:e8:d2:d6", "LEVEL": -70.0, "y": "238"}], "466, 121": [{"std_dev": 13.999999999999979, "x": "466", "ave_count": 5, "MAC": "58:f3:9c:e5:a8:36", "LEVEL": -67.0, "y": "121"}], "433, 478": [{"std_dev": 379.19999999999993, "x": "433", "ave_count": 5, "MAC": "58:f3:9c:e3:00:59", "LEVEL": -81.4, "y": "478"}], "650, 271": [{"std_dev": 18.0, "x": "650", "ave_count": 5, "MAC": "58:f3:9c:cd:c9:36", "LEVEL": -86.0, "y": "271"}], "177, 310": [{"std_dev": 0.0, "x": "177", "ave_count": 1, "MAC": "10:05:ca:71:ed:3d", "LEVEL": -65.0, "y": "310"}], "353, 337": [{"std_dev": 0.0, "x": "353", "ave_count": 1, "MAC": "58:f3:9c:c7:51:f1", "LEVEL": -90.0, "y": "337"}], "593, 256": [{"std_dev": 34.800000000000026, "x": "593", "ave_count": 5, "MAC": "58:f3:9c:78:d5:b6", "LEVEL": -60.8, "y": "256"}], "585, 104": [{"std_dev": 9.200000000000003, "x": "585", "ave_count": 5, "MAC": "58:f3:9c:ac:fa:82", "LEVEL": -48.6, "y": "104"}], "417, 225": [{"std_dev": 83.99999999999999, "x": "417", "ave_count": 5, "MAC": "58:f3:9c:d0:19:96", "LEVEL": -56.0, "y": "225"}], "217, 278": [{"std_dev": 323.0, "x": "217", "ave_count": 4, "MAC": "58:f3:9c:de:d9:03", "LEVEL": -76.5, "y": "278"}], "514, 91": [{"std_dev": 0.0, "x": "514", "ave_count": 1, "MAC": "00:13:10:33:46:1a", "LEVEL": -83.0, "y": "91"}], "353, 369": [{"std_dev": 0.0, "x": "353", "ave_count": 1, "MAC": "10:05:ca:80:fb:86", "LEVEL": -85.0, "y": "369"}], "94, 312": [{"std_dev": 29.200000000000024, "x": "94", "ave_count": 5, "MAC": "58:f3:9c:e8:33:f6", "LEVEL": -81.6, "y": "312"}], "409, 273": [{"std_dev": 0.0, "x": "409", "ave_count": 5, "MAC": "58:f3:9c:d0:19:92", "LEVEL": -69.0, "y": "273"}], "847, 153": [{"std_dev": 51.20000000000002, "x": "847", "ave_count": 5, "MAC": "d0:72:dc:b0:54:15", "LEVEL": -85.4, "y": "153"}], "814, 229": [{"std_dev": 0.0, "x": "814", "ave_count": 1, "MAC": "74:26:ac:b4:8b:cc", "LEVEL": -81.0, "y": "229"}], "277, 223": [{"std_dev": 0.0, "x": "277", "ave_count": 1, "MAC": "58:f3:9c:de:d9:06", "LEVEL": -89.0, "y": "223"}], "829, 264": [{"std_dev": 6.800000000000006, "x": "829", "ave_count": 5, "MAC": "d0:72:dc:01:28:46", "LEVEL": -56.8, "y": "264"}], "726, 250": [{"std_dev": 0.0, "x": "726", "ave_count": 1, "MAC": "58:f3:9c:e8:d2:dc", "LEVEL": -54.0, "y": "250"}], "91, 202": [{"std_dev": 0.0, "x": "91", "ave_count": 1, "MAC": "58:f3:9c:c7:43:49", "LEVEL": -79.0, "y": "202"}], "853, 225": [{"std_dev": 15.200000000000003, "x": "853", "ave_count": 5, "MAC": "d0:72:dc:01:28:46", "LEVEL": -37.4, "y": "225"}], "758, 192": [{"std_dev": 0.0, "x": "758", "ave_count": 1, "MAC": "58:f3:9c:e8:d2:dd", "LEVEL": -82.0, "y": "192"}], "571, 105": [{"std_dev": 251.19999999999996, "x": "571", "ave_count": 5, "MAC": "58:f3:9c:ac:fa:82", "LEVEL": -78.6, "y": "105"}], "882, 234": [{"std_dev": 627.1999999999998, "x": "882", "ave_count": 5, "MAC": "d0:72:dc:01:1a:02", "LEVEL": -83.4, "y": "234"}], "466, 479": [{"std_dev": 0.0, "x": "466", "ave_count": 1, "MAC": "58:f3:9c:e3:00:59", "LEVEL": -85.0, "y": "479"}], "361, 381": [{"std_dev": 0.0, "x": "361", "ave_count": 1, "MAC": "58:f3:9c:e8:38:96", "LEVEL": -83.0, "y": "381"}], "271, 312": [{"std_dev": 102.0, "x": "271", "ave_count": 5, "MAC": "58:f3:9c:e8:38:96", "LEVEL": -71.0, "y": "312"}], "75, 298": [{"std_dev": 0.0, "x": "75", "ave_count": 1, "MAC": "58:f3:9c:bb:90:66", "LEVEL": -82.0, "y": "298"}], "782, 128": [{"std_dev": 1.20000000000001, "x": "782", "ave_count": 5, "MAC": "58:f3:9c:bf:e2:45", "LEVEL": -73.6, "y": "128"}], "577, 144": [{"std_dev": 0.0, "x": "577", "ave_count": 1, "MAC": "58:f3:9c:ac:fa:86", "LEVEL": -80.0, "y": "144"}], "219, 259": [{"std_dev": 0.0, "x": "219", "ave_count": 1, "MAC": "58:f3:9c:e2:f7:6c", "LEVEL": -86.0, "y": "259"}], "487, 478": [{"std_dev": 18.799999999999997, "x": "487", "ave_count": 5, "MAC": "10:05:ca:73:83:56", "LEVEL": -31.2, "y": "478"}], "75, 558": [{"std_dev": 28.800000000000004, "x": "75", "ave_count": 5, "MAC": "58:f3:9c:e3:00:36", "LEVEL": -74.2, "y": "558"}], "769, 147": [{"std_dev": 19.199999999999996, "x": "769", "ave_count": 5, "MAC": "58:f3:9c:bf:e2:45", "LEVEL": -62.4, "y": "147"}], "134, 563": [{"std_dev": 0.0, "x": "134", "ave_count": 1, "MAC": "58:f3:9c:e3:05:d2", "LEVEL": -84.0, "y": "563"}], "534, 106": [{"std_dev": 0.0, "x": "534", "ave_count": 5, "MAC": "58:f3:9c:ac:fa:82", "LEVEL": -80.0, "y": "106"}], "144, 313": [{"std_dev": 18.800000000000008, "x": "144", "ave_count": 5, "MAC": "58:f3:9c:bb:86:1d", "LEVEL": -71.2, "y": "313"}], "528, 255": [{"std_dev": 27.199999999999985, "x": "528", "ave_count": 5, "MAC": "58:f3:9c:d0:19:e9", "LEVEL": -82.6, "y": "255"}], "712, 218": [{"std_dev": 0.0, "x": "712", "ave_count": 5, "MAC": "58:f3:9c:e8:d2:dd", "LEVEL": -82.0, "y": "218"}], "394, 315": [{"std_dev": 0.0, "x": "394", "ave_count": 1, "MAC": "58:f3:9c:d7:95:fc", "LEVEL": -84.0, "y": "315"}], "170, 223": [{"std_dev": 0.0, "x": "170", "ave_count": 5, "MAC": "58:f3:9c:e5:a1:bd", "LEVEL": -61.0, "y": "223"}], "464, 72": [{"std_dev": 5.200000000000003, "x": "464", "ave_count": 5, "MAC": "58:f3:9c:e5:a8:36", "LEVEL": -63.4, "y": "72"}], "63, 296": [{"std_dev": 0.0, "x": "63", "ave_count": 1, "MAC": "10:05:ca:65:ca:c6", "LEVEL": -91.0, "y": "296"}], "416, 204": [{"std_dev": 50.0, "x": "416", "ave_count": 5, "MAC": "58:f3:9c:d0:19:96", "LEVEL": -66.0, "y": "204"}], "485, 257": [{"std_dev": 0.0, "x": "485", "ave_count": 1, "MAC": "00:21:d8:49:16:6d", "LEVEL": -63.0, "y": "257"}], "72, 488": [{"std_dev": 14.800000000000018, "x": "72", "ave_count": 5, "MAC": "58:f3:9c:e4:6e:f6", "LEVEL": -74.2, "y": "488"}], "610, 119": [{"std_dev": 94.0, "x": "610", "ave_count": 5, "MAC": "58:f3:9c:ac:fa:86", "LEVEL": -65.0, "y": "119"}], "836, 191": [{"std_dev": 714.8000000000002, "x": "836", "ave_count": 5, "MAC": "d0:72:dc:01:28:46", "LEVEL": -77.8, "y": "191"}], "817, 180": [{"std_dev": 0.0, "x": "817", "ave_count": 1, "MAC": "d0:72:dc:01:28:46", "LEVEL": -83.0, "y": "180"}], "887, 215": [{"std_dev": 62.79999999999997, "x": "887", "ave_count": 5, "MAC": "d0:72:dc:01:1a:02", "LEVEL": -56.2, "y": "215"}], "81, 484": [{"std_dev": 22.79999999999999, "x": "81", "ave_count": 5, "MAC": "58:f3:9c:e4:6e:f6", "LEVEL": -65.8, "y": "484"}], "85, 448": [{"std_dev": 0.0, "x": "85", "ave_count": 1, "MAC": "10:05:ca:88:76:f9", "LEVEL": -84.0, "y": "448"}], "807, 259": [{"std_dev": 0.0, "x": "807", "ave_count": 2, "MAC": "d0:72:dc:01:28:46", "LEVEL": -88.0, "y": "259"}], "515, 103": [{"std_dev": 0.0, "x": "515", "ave_count": 1, "MAC": "58:f3:9c:ac:fa:82", "LEVEL": -37.0, "y": "103"}], "616, 254": [{"std_dev": 20.000000000000004, "x": "616", "ave_count": 5, "MAC": "58:f3:9c:78:d5:b6", "LEVEL": -73.0, "y": "254"}], "745, 214": [{"std_dev": 4.799999999999983, "x": "745", "ave_count": 5, "MAC": "58:f3:9c:e8:d2:dd", "LEVEL": -82.8, "y": "214"}], "333, 386": [{"std_dev": 199.9999999999999, "x": "333", "ave_count": 5, "MAC": "58:f3:9c:e4:79:ad", "LEVEL": -81.0, "y": "386"}], "76, 526": [{"std_dev": 0.0, "x": "76", "ave_count": 1, "MAC": "58:f3:9c:e4:6e:f6", "LEVEL": -75.0, "y": "526"}], "967, 284": [{"std_dev": 0.0, "x": "967", "ave_count": 1, "MAC": "58:f3:9c:f5:dc:56", "LEVEL": -67.0, "y": "284"}], "409, 314": [{"std_dev": 0.0, "x": "409", "ave_count": 5, "MAC": "58:f3:9c:af:d4:7d", "LEVEL": -58.0, "y": "314"}], "216, 296": [{"std_dev": 0.0, "x": "216", "ave_count": 1, "MAC": "00:23:eb:d1:f6:49", "LEVEL": -76.0, "y": "296"}], "71, 199": [{"std_dev": 4.800000000000011, "x": "71", "ave_count": 5, "MAC": "10:05:ca:71:ed:36", "LEVEL": -88.8, "y": "199"}], "356, 470": [{"std_dev": 0.0, "x": "356", "ave_count": 1, "MAC": "58:f3:9c:e1:47:e6", "LEVEL": -78.0, "y": "470"}], "683, 271": [{"std_dev": 0.0, "x": "683", "ave_count": 1, "MAC": "58:f3:9c:cd:c9:36", "LEVEL": -89.0, "y": "271"}], "821, 214": [{"std_dev": 0.0, "x": "821", "ave_count": 1, "MAC": "d0:72:dc:01:1a:06", "LEVEL": -85.0, "y": "214"}], "628, 254": [{"std_dev": 29.999999999999964, "x": "628", "ave_count": 5, "MAC": "58:f3:9c:78:d5:b6", "LEVEL": -68.0, "y": "254"}], "876, 105": [{"std_dev": 0.0, "x": "876", "ave_count": 1, "MAC": "d0:72:dc:aa:a6:2d", "LEVEL": -69.0, "y": "105"}], "872, 190": [{"std_dev": 0.0, "x": "872", "ave_count": 1, "MAC": "d0:72:dc:aa:a1:36", "LEVEL": -61.0, "y": "190"}], "304, 315": [{"std_dev": 105.20000000000007, "x": "304", "ave_count": 5, "MAC": "58:f3:9c:e8:38:96", "LEVEL": -67.4, "y": "315"}], "716, 269": [{"std_dev": 13.199999999999992, "x": "716", "ave_count": 5, "MAC": "58:f3:9c:e8:d2:dc", "LEVEL": -55.6, "y": "269"}], "456, 255": [{"std_dev": 0.0, "x": "456", "ave_count": 1, "MAC": "00:21:d8:49:47:53", "LEVEL": -68.0, "y": "255"}], "464, 56": [{"std_dev": 1.20000000000001, "x": "464", "ave_count": 5, "MAC": "58:f3:9c:e5:a8:36", "LEVEL": -76.6, "y": "56"}], "865, 127": [{"std_dev": 0.0, "x": "865", "ave_count": 1, "MAC": "d0:72:dc:b0:54:15", "LEVEL": -87.0, "y": "127"}], "857, 160": [{"std_dev": 0.0, "x": "857", "ave_count": 1, "MAC": "d0:72:dc:aa:a6:29", "LEVEL": -69.0, "y": "160"}], "568, 253": [{"std_dev": 0.0, "x": "568", "ave_count": 1, "MAC": "58:f3:9c:d0:19:e9", "LEVEL": -84.0, "y": "253"}], "121, 222": [{"std_dev": 7.199999999999999, "x": "121", "ave_count": 5, "MAC": "58:f3:9c:c7:43:49", "LEVEL": -74.4, "y": "222"}], "145, 226": [{"std_dev": 0.0, "x": "145", "ave_count": 1, "MAC": "58:f3:9c:e5:a1:bd", "LEVEL": -61.0, "y": "226"}], "524, 123": [{"std_dev": 0.0, "x": "524", "ave_count": 5, "MAC": "58:f3:9c:ac:fa:82", "LEVEL": -80.0, "y": "123"}], "76, 313": [{"std_dev": 0.0, "x": "76", "ave_count": 1, "MAC": "58:f3:9c:e8:33:f6", "LEVEL": -86.0, "y": "313"}], "74, 338": [{"std_dev": 6.800000000000011, "x": "74", "ave_count": 5, "MAC": "10:05:ca:42:0b:e9", "LEVEL": -70.2, "y": "338"}], "334, 312": [{"std_dev": 0.0, "x": "334", "ave_count": 1, "MAC": "10:05:ca:80:fb:86", "LEVEL": -67.0, "y": "312"}], "76, 374": [{"std_dev": 0.0, "x": "76", "ave_count": 1, "MAC": "10:05:ca:42:0b:e9", "LEVEL": -71.0, "y": "374"}], "464, 225": [{"std_dev": 0.0, "x": "464", "ave_count": 1, "MAC": "58:f3:9c:d0:19:92", "LEVEL": -90.0, "y": "225"}], "93, 222": [{"std_dev": 3.20000000000001, "x": "93", "ave_count": 5, "MAC": "58:f3:9c:c7:43:49", "LEVEL": -79.4, "y": "222"}], "438, 143": [{"std_dev": 2.0, "x": "438", "ave_count": 2, "MAC": "58:f3:9c:e4:80:56", "LEVEL": -90.0, "y": "143"}], "391, 49": [{"std_dev": 0.0, "x": "391", "ave_count": 1, "MAC": "58:f3:9c:e8:55:36", "LEVEL": -55.0, "y": "49"}], "504, 256": [{"std_dev": 6.800000000000004, "x": "504", "ave_count": 5, "MAC": "58:f3:9c:d0:19:e9", "LEVEL": -76.2, "y": "256"}], "408, 447": [{"std_dev": 0.0, "x": "408", "ave_count": 1, "MAC": "10:05:ca:73:83:56", "LEVEL": -59.0, "y": "447"}], "793, 113": [{"std_dev": 60.5, "x": "793", "ave_count": 2, "MAC": "58:f3:9c:bf:e2:45", "LEVEL": -79.5, "y": "113"}], "410, 413": [{"std_dev": 0.0, "x": "410", "ave_count": 1, "MAC": "58:f3:9c:e2:f4:c2", "LEVEL": -80.0, "y": "413"}], "243, 313": [{"std_dev": 14.799999999999983, "x": "243", "ave_count": 5, "MAC": "58:f3:9c:e8:38:96", "LEVEL": -69.2, "y": "313"}], "889, 92": [{"std_dev": 18.80000000000001, "x": "889", "ave_count": 5, "MAC": "d0:72:dc:aa:a1:36", "LEVEL": -63.2, "y": "92"}], "463, 144": [{"std_dev": 28.799999999999983, "x": "463", "ave_count": 5, "MAC": "58:f3:9c:e5:a8:36", "LEVEL": -84.8, "y": "144"}], "627, 235": [{"std_dev": 0.0, "x": "627", "ave_count": 1, "MAC": "58:f3:9c:78:d5:b6", "LEVEL": -70.0, "y": "235"}], "908, 248": [{"std_dev": 0.0, "x": "908", "ave_count": 1, "MAC": "d0:72:dc:01:1a:02", "LEVEL": -89.0, "y": "248"}], "375, 383": [{"std_dev": 0.0, "x": "375", "ave_count": 5, "MAC": "58:f3:9c:e8:38:92", "LEVEL": -89.0, "y": "383"}], "75, 421": [{"std_dev": 24.800000000000015, "x": "75", "ave_count": 5, "MAC": "10:05:ca:88:76:f6", "LEVEL": -78.8, "y": "421"}], "556, 143": [{"std_dev": 0.0, "x": "556", "ave_count": 5, "MAC": "58:f3:9c:ac:fa:82", "LEVEL": -80.0, "y": "143"}], "416, 93": [{"std_dev": 166.00000000000006, "x": "416", "ave_count": 5, "MAC": "58:f3:9c:e8:55:36", "LEVEL": -68.0, "y": "93"}], "610, 141": [{"std_dev": 16.800000000000026, "x": "610", "ave_count": 5, "MAC": "58:f3:9c:ac:fa:86", "LEVEL": -77.8, "y": "141"}], "75, 442": [{"std_dev": 10.75000000000001, "x": "75", "ave_count": 4, "MAC": "10:05:ca:88:76:f6", "LEVEL": -83.25, "y": "442"}], "222, 222": [{"std_dev": 0.0, "x": "222", "ave_count": 1, "MAC": "58:f3:9c:bb:86:19", "LEVEL": -82.0, "y": "222"}], "862, 204": [{"std_dev": 341.2, "x": "862", "ave_count": 5, "MAC": "d0:72:dc:01:28:46", "LEVEL": -60.4, "y": "204"}], "601, 104": [{"std_dev": 9.199999999999996, "x": "601", "ave_count": 5, "MAC": "58:f3:9c:ac:fa:82", "LEVEL": -37.4, "y": "104"}], "512, 143": [{"std_dev": 0.0, "x": "512", "ave_count": 5, "MAC": "58:f3:9c:ac:fa:82", "LEVEL": -80.0, "y": "143"}], "355, 311": [{"std_dev": 0.0, "x": "355", "ave_count": 1, "MAC": "58:f3:9c:af:d4:7d", "LEVEL": -58.0, "y": "311"}], "222, 241": [{"std_dev": 72.80000000000003, "x": "222", "ave_count": 5, "MAC": "58:f3:9c:de:d9:03", "LEVEL": -58.8, "y": "241"}], "337, 349": [{"std_dev": 0.0, "x": "337", "ave_count": 1, "MAC": "58:f3:9c:e1:38:2d", "LEVEL": -72.0, "y": "349"}], "416, 177": [{"std_dev": 63.2, "x": "416", "ave_count": 5, "MAC": "58:f3:9c:d0:19:96", "LEVEL": -58.4, "y": "177"}], "441, 224": [{"std_dev": 816.6666666666667, "x": "441", "ave_count": 3, "MAC": "58:f3:9c:d0:19:96", "LEVEL": -76.33333333333333, "y": "224"}], "384, 469": [{"std_dev": 38.79999999999999, "x": "384", "ave_count": 5, "MAC": "58:f3:9c:e3:00:59", "LEVEL": -60.2, "y": "469"}], "631, 267": [{"std_dev": 4.799999999999997, "x": "631", "ave_count": 5, "MAC": "58:f3:9c:cd:c9:36", "LEVEL": -67.8, "y": "267"}], "545, 478": [{"std_dev": 9.999999999999995, "x": "545", "ave_count": 5, "MAC": "10:05:ca:73:83:56", "LEVEL": -58.0, "y": "478"}], "417, 51": [{"std_dev": 9.199999999999992, "x": "417", "ave_count": 5, "MAC": "58:f3:9c:e8:55:36", "LEVEL": -54.6, "y": "51"}], "417, 114": [{"std_dev": 100.8, "x": "417", "ave_count": 5, "MAC": "58:f3:9c:e8:55:36", "LEVEL": -47.8, "y": "114"}], "844, 174": [{"std_dev": 0.0, "x": "844", "ave_count": 1, "MAC": "d0:72:dc:b0:51:8c", "LEVEL": -60.0, "y": "174"}], "931, 265": [{"std_dev": 0.0, "x": "931", "ave_count": 1, "MAC": "58:f3:9c:f5:dc:06", "LEVEL": -82.0, "y": "265"}], "951, 274": [{"std_dev": 6.75, "x": "951", "ave_count": 4, "MAC": "58:f3:9c:f3:73:a6", "LEVEL": -86.25, "y": "274"}], "409, 298": [{"std_dev": 0.0, "x": "409", "ave_count": 1, "MAC": "58:f3:9c:d0:19:92", "LEVEL": -69.0, "y": "298"}], "839, 247": [{"std_dev": 210.80000000000004, "x": "839", "ave_count": 5, "MAC": "d0:72:dc:01:28:46", "LEVEL": -58.8, "y": "247"}], "408, 253": [{"std_dev": 0.0, "x": "408", "ave_count": 1, "MAC": "58:f3:9c:d0:19:56", "LEVEL": -89.0, "y": "253"}], "793, 218": [{"std_dev": 0.0, "x": "793", "ave_count": 1, "MAC": "74:26:ac:b4:8b:c6", "LEVEL": -85.0, "y": "218"}], "411, 474": [{"std_dev": 29.199999999999992, "x": "411", "ave_count": 5, "MAC": "58:f3:9c:e3:00:59", "LEVEL": -66.6, "y": "474"}], "726, 203": [{"std_dev": 0.0, "x": "726", "ave_count": 5, "MAC": "58:f3:9c:e8:d2:dd", "LEVEL": -82.0, "y": "203"}], "486, 144": [{"std_dev": 0.0, "x": "486", "ave_count": 1, "MAC": "58:f3:9c:e5:a8:36", "LEVEL": -80.0, "y": "144"}], "390, 380": [{"std_dev": 0.0, "x": "390", "ave_count": 1, "MAC": "58:f3:9c:e8:38:92", "LEVEL": -89.0, "y": "380"}], "780, 156": [{"std_dev": 0.0, "x": "780", "ave_count": 2, "MAC": "c0:c1:c0:7c:46:ce", "LEVEL": -62.0, "y": "156"}]}]}